{
  "pubblicato": true,
  "tipologia": "Terreno",
  "sottotipologia": "Terreno edificabile",
  "titolo": "Terreno edificabile con vista colline — 3.200 mq",
  "indirizzo": "Via del Prato 8",
  "citta": "San Giovanni Valdarno",
  "provincia": "AR",
  "cap": "52027",
  "offerta_minima": 95000,
  "descrizione": "Terreno edificabile di 3.200 mq in posizione panoramica con vista sulle colline toscane. Zona B2, ben servito da infrastrutture. Ottima opportunità per sviluppo residenziale.",
  "foto_copertina": "",
  "galleria": [],
  "data_pubblicazione": "2025-01-20",
  "in_evidenza": false
}
